pulseapi_integration_calibrate/__init__.py
pulseapi_integration_calibrate/plane.py
pulseapi_integration_calibrate/robodk.py
pulseapi_integration_calibrate/show_axes.py
pulseapi_integration_calibrate-0.0.3.dist-info/LICENSE
pulseapi_integration_calibrate-0.0.3.dist-info/METADATA
pulseapi_integration_calibrate-0.0.3.dist-info/WHEEL
pulseapi_integration_calibrate-0.0.3.dist-info/top_level.txt
pulseapi_integration_calibrate-0.0.3.dist-info/RECORD
